fast_hist_package/__init__.py
fast_hist_package/module_fast_hist.py
fast_hist_package/module_fast_hist_1.py
tycoon_fast_hist-0.1.0.dist-info/METADATA
tycoon_fast_hist-0.1.0.dist-info/WHEEL
tycoon_fast_hist-0.1.0.dist-info/top_level.txt
tycoon_fast_hist-0.1.0.dist-info/RECORD
